LICENSE.txt
MANIFEST.in
README.md
setup.cfg
setup.py
codetf/__init__.py
codetf/code_utility/__init__.py
codetf/code_utility/ast_parser.py
codetf/code_utility/base_utility.py
codetf/code_utility/language_specific_utility.py
codetf/code_utility/apex/__init__.py
codetf/code_utility/apex/apex_code_utility.py
codetf/code_utility/java/__init__.py
codetf/code_utility/java/java_code_utility.py
codetf/code_utility/python/__init__.py
codetf/code_utility/python/python_code_utility.py
codetf/common/__init__.py
codetf/common/registry.py
codetf/common/utils.py
codetf/configs/__init__.py
codetf/configs/default.yaml
codetf/configs/dataset/dataset.yaml
codetf/configs/inference/bert.yaml
codetf/configs/inference/causal_lm.yaml
codetf/configs/inference/codet5.yaml
codetf/configs/training/causal_lm.yaml
codetf/configs/training/codet5.yaml
codetf/data_utility/__init__.py
codetf/data_utility/apps_dataset.py
codetf/data_utility/base_dataset.py
codetf/data_utility/codexglue_dataset.py
codetf/data_utility/human_eval_dataset.py
codetf/data_utility/mpp_dataset.py
codetf/data_utility/stackexchange_instruction_dataset.py
codetf/data_utility/util.py
codetf/models/__init__.py
codetf/models/base_model.py
codetf/models/bert_models/__init__.py
codetf/models/causal_lm_models/__init__.py
codetf/models/seq2seq_models/__init__.py
codetf/performance/__init__.py
codetf/performance/evaluation_metric.py
codetf/performance/model_evaluator.py
codetf/trainer/base_trainer.py
codetf/trainer/causal_lm_trainer.py
codetf/trainer/codet5_trainer.py
codetf/tree-sitter-prebuilts/Darwin/apex.so
codetf/tree-sitter-prebuilts/Darwin/bash.so
codetf/tree-sitter-prebuilts/Darwin/c.so
codetf/tree-sitter-prebuilts/Darwin/c_sharp.so
codetf/tree-sitter-prebuilts/Darwin/cpp.so
codetf/tree-sitter-prebuilts/Darwin/css.so
codetf/tree-sitter-prebuilts/Darwin/elm.so
codetf/tree-sitter-prebuilts/Darwin/go.so
codetf/tree-sitter-prebuilts/Darwin/haskell.so
codetf/tree-sitter-prebuilts/Darwin/html.so
salesforce_codetf.egg-info/PKG-INFO
salesforce_codetf.egg-info/SOURCES.txt
salesforce_codetf.egg-info/dependency_links.txt
salesforce_codetf.egg-info/not-zip-safe
salesforce_codetf.egg-info/requires.txt
salesforce_codetf.egg-info/top_level.txt
