Metadata-Version: 2.1
Name: salesforce-codetf
Version: 1.0.2.3
Summary: CodeTF: A Transformer-based Library for Code Intelligence
Home-page: https://github.com/Salesforce/CodeTF
Author: Nghi D. Q. Bui
License: Apache 2.0
Keywords: AI4Code,Code Intelligence,Generative AI,Deep Learning,Library,PyTorch,HuggingFace
Requires-Python: >=3.8.0
License-File: LICENSE.txt
